{"parentNames":["IDN","RIAU","INDRAGIRI HILIR","PELANGIRAN"],"id":14888,"kpu":[null,{"tSah":2,"sah":200,"pas2":168,"pas1":32,"jum":202},{"tSah":2,"sah":174,"pas2":139,"pas1":35,"jum":176},{"pas2":205,"pas1":24,"jum":229,"tSah":0,"sah":229},{"tSah":3,"sah":154,"pas2":103,"pas1":51,"jum":157},{"tSah":3,"sah":231,"pas2":173,"pas1":58,"jum":239},{"tSah":1,"sah":132,"pas2":88,"pas1":44,"jum":133},{"tSah":2,"sah":133,"pas2":94,"pas1":39,"jum":135},{"tSah":1,"sah":143,"pas2":105,"pas1":38,"jum":144},{"tSah":4,"sah":156,"pas2":54,"pas1":102,"jum":160},{"pas1":83,"jum":140,"tSah":1,"sah":139,"pas2":56},{"pas1":61,"jum":93,"tSah":1,"sah":92,"pas2":31},{"sah":132,"pas2":76,"pas1":56,"jum":139,"tSah":7},{"pas1":38,"jum":82,"tSah":3,"sah":79,"pas2":41},{"tSah":0,"sah":67,"pas2":50,"pas1":17,"jum":67},{"tSah":0,"sah":142,"pas2":104,"pas1":38,"jum":142},{"pas1":54,"jum":113,"tSah":1,"sah":112,"pas2":58}],"depth":4,"data":{"1":{"c1":null,"photos":{"http://lh3.googleusercontent.com/FkevktD2zQynfWIYCJ45aP8_48Es4Z5J0njiT-cVdsWit-1kqA6fbaleN090diRq2GNkN3oRjHq-2sU-x-4v":{"c1":{"plano":2,"halaman":"1","type":1},"sum":{"pending":0,"jum":202},"ts":1556683039747},"http://lh3.googleusercontent.com/xpfbjPHpn4NZX-Op6HZ4uA28zPyw6woFNbypWBfWWkvpnD9mQc1nIZCAzkQ8jbgoqEHDqkkKBeOZDrlvqPg":{"ts":1556683036218,"c1":{"type":1,"plano":2,"halaman":"2"},"sum":{"tSah":2,"sah":200,"pas2":168,"pas1":32}}},"sum":{"janggal":0,"cakupan":1,"pas1":32,"jum":202,"pending":0,"pas2":168,"tSah":2,"sah":200},"ts":1556683039747},"2":{"photos":{"http://lh3.googleusercontent.com/tbj1q07pIDPRDKPvG1sU1Y5fLP_qHbPZRdTdI0yuhV0UjOsfBCnX4aXyFqIAG7gFQhK11PALGVNegQF5_g":{"sum":{"tSah":2,"sah":174,"pas2":139,"pas1":35},"ts":1556427002887,"c1":{"type":1,"plano":2,"halaman":"2"}},"http://lh3.googleusercontent.com/P-aNT5fuC91cZBY1I_rRE0EX8pUcfPUpxdzwTWaX4bGPUSMgXRGuKoeTvPP5-5Ko89M6vVqa1D5MmLNQX_A":{"c1":{"type":1,"plano":2,"halaman":"1"},"sum":{"jum":176,"pending":0},"ts":1556427006229}},"sum":{"tSah":2,"sah":174,"janggal":0,"cakupan":1,"pas1":35,"jum":176,"pending":0,"pas2":139},"ts":1556427006229,"c1":null},"3":{"photos":{"http://lh3.googleusercontent.com/SrzLMOhnySm1AbeNrt4IwjTYlEjP7PVbq5JTiJYxCivR3HpKr4LVqv3V9L4xecQcwxwa_clQGte45_CorkkR":{"sum":{"tSah":0,"sah":229,"pending":0,"pas2":205,"pas1":24},"ts":1556427016943,"c1":{"type":1,"plano":2,"halaman":"2"}},"http://lh3.googleusercontent.com/5808_nXhBc8PYAHcmFbVg5_4DsVER-gIhgam42n0Mp4yIFFoBjql0pPfGH6Fmg0zYoyAfnQx7AyB7TcH0NPe":{"c1":{"type":1,"plano":2,"halaman":"1"},"sum":{"jum":229},"ts":1556427012361}},"sum":{"pending":0,"pas2":205,"tSah":0,"sah":229,"janggal":0,"cakupan":1,"pas1":24,"jum":229},"ts":1556427016943,"c1":null},"4":{"c1":null,"photos":{"http://lh3.googleusercontent.com/8v_w-kw-epIdQuEah7Ha54NDpzzujmAmRdnTNemKfdoRpVGqVI9G6XLrJZ1RLfYPM3hPwHH_3yFZdPsZXw":{"c1":{"plano":1,"halaman":"2","type":1},"sum":{"sah":154,"pas2":103,"pas1":51,"tSah":3},"ts":1555524041766},"http://lh3.googleusercontent.com/EmWwKjwA4Ua5-NT9o0p6o8iB_QcTOsunIjUIftvXIWm0Slv4S9_CLEnan-dPC7i4rISZFaaPJJGfOd_GLtA":{"ts":1556427049382,"c1":{"plano":2,"halaman":"1","type":1},"sum":{"pending":0,"jum":157}},"http://lh3.googleusercontent.com/SZtMaaUcMBY15TAQo4ziyC4gxS7Wxzcq_CvejGciXbXAp0QWec-ne0Wp4VaBJ9FQ80FXOTR-SCK6LUDoYzc":{"sum":{"tSah":3,"sah":154,"pas2":103,"pas1":51},"ts":1556427023545,"c1":{"type":1,"plano":2,"halaman":"2"}}},"sum":{"janggal":0,"cakupan":1,"pas1":51,"jum":157,"pending":0,"pas2":103,"tSah":3,"sah":154},"ts":1556427049382},"5":{"ts":1557114842239,"c1":null,"photos":{"http://lh3.googleusercontent.com/kqgP2teOADg14SgVnD8GQWo1x5bwHd9N6YZ-6KE00TYUemCR6MbmLz-qRoOZ9vD3h8qBvfku4SJ4c5vYAy4":{"sum":{"pending":0,"error":0,"jum":234},"ts":1557114842239,"c1":{"halaman":"1","type":1,"plano":2}},"http://lh3.googleusercontent.com/FYy9o2oE_BMt85Dx2hw7_5PPcwDaIw8TjlX2a8KmdDMULF8WxlQajIY3nN_JkJP2m--yoeDwY-mRjWtTrA":{"c1":{"type":1,"plano":2,"halaman":"2"},"sum":{"pas1":58,"tSah":3,"sah":231,"pending":0,"pas2":173},"ts":1556427056447}},"sum":{"pending":0,"pas2":173,"tSah":3,"sah":231,"laporKpu":0,"janggal":0,"error":0,"cakupan":1,"pas1":58,"jum":234}},"6":{"c1":null,"photos":{"http://lh3.googleusercontent.com/MO8l6gDd5ImF6saNr-hVcvr1YO-uowd4qPUACMmrOEfPfduxiJA1NiBbRqdPTCv5bTiL2LJSok-v5MScy2o":{"ts":1556427072615,"c1":{"type":1,"plano":2,"halaman":"1"},"sum":{"pending":0,"jum":133}},"http://lh3.googleusercontent.com/LVYXU8hqiR8tyOK2m79QTg732R6oF4VAiwloVe6Mgts5kzo6iPwZkiPt1RpYSAoe20mX6flfXeiIeZRM-2M":{"sum":{"tSah":1,"sah":132,"pas2":88,"pas1":44},"ts":1556427067941,"c1":{"plano":2,"halaman":"2","type":1}}},"sum":{"janggal":0,"cakupan":1,"pas1":44,"jum":133,"pending":0,"pas2":88,"tSah":1,"sah":132},"ts":1556427072615},"7":{"c1":null,"photos":{"http://lh3.googleusercontent.com/GUe47cuZUhB4HEFKQmCxlc-_0sCc4noaLgaQjmTi8ZgLrrQAiG3glQZmT_aPiCufiDSmSyEz0r8DNESqcbc":{"sum":{"pas1":39,"tSah":2,"sah":133,"pas2":94},"ts":1556427079832,"c1":{"type":1,"plano":2,"halaman":"2"}},"http://lh3.googleusercontent.com/MvPgekQLm_CRkhdEULmCwPMsWy3ed2RkZfCd5bn92H5Ax3TOeW80kQSFcO7DcxINsViRq9xYl41eOR2RG9DG":{"sum":{"pending":0,"jum":135},"ts":1556427090819,"c1":{"type":1,"plano":2,"halaman":"1"}}},"sum":{"janggal":0,"cakupan":1,"pas1":39,"jum":135,"pending":0,"pas2":94,"tSah":2,"sah":133},"ts":1556427090819},"8":{"ts":1556427111053,"c1":null,"photos":{"http://lh3.googleusercontent.com/BoANZTCHC9E9E5_R6ud4g_-d0dSrhNqT9_wqJMtwSpsaK2ZmhweCCPxwxSXkGIchM1cwldGHP0GskvkcSXta":{"sum":{"jum":144,"pending":0},"ts":1556427111053,"c1":{"plano":2,"halaman":"1","type":1}},"http://lh3.googleusercontent.com/FWThR_hE3D6CleTW0QrVEV1ZKf5PO8G_DMX7FFs96Qw1fL4HRu8KmFw-jcJV6woPhMXzJoUNVM9_Nw26mUk":{"c1":{"type":1,"plano":2,"halaman":"2"},"sum":{"tSah":1,"sah":143,"pas2":105,"pas1":38},"ts":1556427106620}},"sum":{"tSah":1,"sah":143,"janggal":0,"cakupan":1,"pas1":38,"jum":144,"pending":0,"pas2":105}},"9":{"photos":{"http://lh3.googleusercontent.com/Os5LiFJ5oLuK5EhvdJLegaB7Lo0n8h4S9Ss8XMQFpGQm3_imS4Yw4CH13Zucmsi631BvUWupLnJ6igR0BbWp":{"c1":{"type":1,"plano":2,"halaman":"2"},"sum":{"sah":156,"pending":0,"pas2":54,"pas1":102,"tSah":4},"ts":1556765460169},"http://lh3.googleusercontent.com/xQOd1jE7QUufb-gNaroaQS9fSl8-TTn34IsSShPhYv9j_F_pIFqaYuAJSzwQXe4aoeyirmz2jkVTHIgmig":{"c1":{"type":1,"plano":2,"halaman":"1"},"sum":{"jum":160},"ts":1556427126389}},"sum":{"tSah":4,"sah":156,"janggal":0,"cakupan":1,"pas1":102,"jum":160,"pending":0,"pas2":54},"ts":1556765460169,"c1":null},"10":{"c1":null,"photos":{"http://lh3.googleusercontent.com/C52lvZ78Rw7zvCVf7Bvy1RlmaPVGO3MVuPOZnIpOmRgNVoT7LBKGSu8tkzgt3_nkMTQE8iA-36Cx7ZMlFGE":{"sum":{"jum":196},"ts":1557114865527,"c1":{"plano":2,"halaman":"1","type":1}},"http://lh3.googleusercontent.com/eLBLqdq5gD_j1V4mOb-3VfXMomiEMH5SXblK229lJEbGaAYEn8vfUtf2n6_jcUPGpoJFEyvSjoglWziYAdU":{"c1":{"plano":2,"halaman":"2","type":1},"sum":{"pas2":56,"pas1":83,"tSah":1,"sah":139},"ts":1556765477291}},"sum":{"tSah":1,"sah":139,"laporKpu":1,"janggal":1,"error":0,"cakupan":1,"pas1":83,"jum":196,"pending":0,"pas2":56},"ts":1557114865527},"11":{"c1":null,"photos":{"http://lh3.googleusercontent.com/7x6UGz-xLzov26tosBwqDhACXJMppD0o9W1WRnRwzwwtb0KoQQdl4Kfk2SH5NsLB2SKy4mBya1W5ogOfekJ3":{"sum":{"tSah":1,"sah":92,"pas2":31,"pas1":61},"ts":1556427138399,"c1":{"type":1,"plano":2,"halaman":"2"}},"http://lh3.googleusercontent.com/ZQb-EYuBhzhJyTs5AhVjgmbGsDQ2qGube0VTVJxo3NkKKAOSQKN3rdA-dhFnWVBQ0QVv0H2G96FLs0Z3nJh9":{"ts":1556427142119,"c1":{"type":1,"plano":2,"halaman":"1"},"sum":{"pending":0,"jum":93}}},"sum":{"pending":0,"pas2":31,"tSah":1,"sah":92,"janggal":0,"cakupan":1,"pas1":61,"jum":93},"ts":1556427142119},"12":{"ts":1558029136603,"c1":null,"photos":{"http://lh3.googleusercontent.com/iqylGTItWcKelhAOoTx6KUnDikK7Jz_6F_0FBkAZc1aOg_WfFAd-XQp8cxY3TWrd_fdjPy1ME2zPKCiM__M":{"c1":{"plano":2,"halaman":"2","type":1},"sum":{"pas1":56,"tSah":7,"sah":132,"pending":0,"pas2":76},"ts":1558029136603},"http://lh3.googleusercontent.com/QrE5VDEgaz9iiJ3lMvrij85dMpJqNKUwXBITk92t2bXaS6s2A6denvDT79jqTkdJNgrUE9VJhCDRGgJyW_BK":{"c1":{"type":1,"plano":2,"halaman":"1"},"sum":{"jum":139},"ts":1558029127665}},"sum":{"tSah":7,"sah":132,"laporKpu":0,"janggal":0,"cakupan":1,"pas1":56,"jum":139,"pending":0,"pas2":76}},"13":{"c1":null,"photos":{"http://lh3.googleusercontent.com/z-B17VlJNyRQ0587PcL5uzdhuuT9GaiJ7pIbpOx-aWlcuE7iYEKqxasYu3lpyN8RzrMYVhq5-31zX7IR4mTv":{"c1":{"plano":2,"halaman":"1","type":1},"sum":{"pending":0,"jum":82},"ts":1556427158934},"http://lh3.googleusercontent.com/hVAJ2FzZp51mcv79UpYNaHcZxF92AyCVDcXAddgNY8Sy6cuya9E0scvJGrgEaU_2TZaZ3Uvqcl6XqQbDl6U":{"c1":{"type":1,"plano":2,"halaman":"2"},"sum":{"pas1":38,"tSah":3,"sah":79,"pas2":41},"ts":1556427155360}},"sum":{"pending":0,"pas2":41,"tSah":3,"sah":79,"janggal":0,"cakupan":1,"pas1":38,"jum":82},"ts":1556427158934},"14":{"c1":null,"photos":{"http://lh3.googleusercontent.com/qJP7H-vO9-mLHQAdf8FJWB1xPLzUZFFUeeDQ4076Ya6TJkNU85DbvYQBrfStLL5yXt-MM-9yzVWm8dpd1PI":{"ts":1556427165395,"c1":{"type":1,"plano":2,"halaman":"2"},"sum":{"tSah":0,"sah":67,"pas2":50,"pas1":17}},"http://lh3.googleusercontent.com/Aoynf9BRUtcTmtxFZbG84TXCu8LXCbRwmQjHOL020QmaopXX4qDqgH-nV7FH0-EbeUv9_dVA7MY-X7ZCLg":{"c1":{"type":1,"plano":2,"halaman":"1"},"sum":{"jum":67,"pending":0},"ts":1556427168773}},"sum":{"cakupan":1,"pas1":17,"jum":67,"pending":0,"pas2":50,"tSah":0,"sah":67,"janggal":0},"ts":1556427168773},"15":{"ts":1556427179356,"c1":null,"photos":{"http://lh3.googleusercontent.com/LSQxHh6X9638v_cHAbyD8ttq-LiOjjI0Hlh__uJxMOKTVkwHAbgOInX9ox_ytnIMXrTPFtQ9b0cyBZAtEpo":{"sum":{"pending":0,"jum":142},"ts":1556427179356,"c1":{"type":1,"plano":2,"halaman":"1"}},"http://lh3.googleusercontent.com/uSG7GPbkRQ7tigWFkzaV2M1p1Ys_ShX7imZtDKjIE7wEv-gqJ7bTipnRGMc1WwpsEYl4SL8xPFUcq1CcZcs":{"ts":1556427175973,"c1":{"plano":2,"halaman":"2","type":1},"sum":{"pas2":104,"pas1":38,"tSah":0,"sah":142}}},"sum":{"pending":0,"pas2":104,"tSah":0,"sah":142,"janggal":0,"cakupan":1,"pas1":38,"jum":142}},"16":{"ts":1556765534918,"c1":null,"photos":{"http://lh3.googleusercontent.com/sHdCYQzmA23FWiyo4yCQxWUBOsn50adMUPmpmD07zJpfEKzPrmJl-7sCNYMFJWUmJ8zE-VvanJctoA-LGg":{"sum":{"pas1":54,"tSah":1,"sah":112,"pas2":58},"ts":1556427204516,"c1":{"type":1,"plano":2,"halaman":"2"}},"http://lh3.googleusercontent.com/FXtHU-mOgieP6mePktjQGaAJsDwZodEhJxELAx2yQ8DcPjGWCCKgwvuJLItZIpta_HaKprrEmpMZQHGs21Q":{"c1":{"halaman":"1","type":1,"plano":2},"sum":{"pending":0,"jum":113},"ts":1556765534918}},"sum":{"tSah":1,"sah":112,"janggal":0,"cakupan":1,"pas1":54,"jum":113,"pending":0,"pas2":58}}},"parentIds":[0,14086,14741,14887],"name":"Rotan Semelur","children":[[1,148,146],[2,120,114],[3,153,146],[4,155,121],[5,159,140],[6,124,117],[7,143,116],[8,120,78],[9,105,112],[10,98,95],[11,74,63],[12,78,76],[13,49,47],[14,94,60],[15,125,115],[16,78,52]]}