{"parentNames":["IDN","BENGKULU","SELUMA","SELUMA"],"id":21729,"kpu":[null,{"tSah":2,"sah":212,"pas2":147,"pas1":65,"jum":214},{"tSah":4,"sah":198,"pas2":99,"pas1":99,"jum":202},{"tSah":4,"sah":251,"pas2":153,"pas1":98,"jum":255},{"pas2":90,"pas1":99,"jum":193,"tSah":4,"sah":193},{"tSah":3,"sah":170,"pas2":112,"pas1":58,"jum":173}],"depth":4,"data":{"1":{"ts":1555942865584,"c1":null,"photos":{"http://lh3.googleusercontent.com/7_4RcJP5XvQCEHgtg9Fg-T8RXgmTmUcfKUvxyFqTGG-S16zFxvnmfdfIHxEoThAFM_YZVVEAU1j954gMNho":{"c1":{"type":1,"plano":2,"halaman":"2"},"sum":{"tSah":2,"sah":212,"pending":0,"pas2":147,"pas1":65},"ts":1555942865584},"http://lh3.googleusercontent.com/UkCiNzpAYNqczZMeitk6WHjfHDcLCf-Tff2ZBNMSI4Uv0Eb2cTIqTTLCA8O-Ks1m3XdN37AGqJwKqxiQWw":{"ts":1555942849327,"c1":{"plano":2,"halaman":"1","type":1},"sum":{"jum":214}}},"sum":{"janggal":0,"cakupan":1,"pas1":65,"jum":214,"pending":0,"pas2":147,"tSah":2,"sah":212}},"2":{"ts":1555942953542,"c1":null,"photos":{"http://lh3.googleusercontent.com/zLHl21oNozXsXtyPEihfYb7-AKfXwUfZm0KT3Wd69RNqGqz0Cuo6jhrdUTr1Ix4MQ2NvU_lCssX9LbKd6hk":{"sum":{"tSah":4,"sah":198,"pending":0,"pas2":99,"pas1":99},"ts":1555942953542,"c1":{"type":1,"plano":2,"halaman":"2"}},"http://lh3.googleusercontent.com/vT87HrWARJQ4nxTycIYojiu6V6r5E-m6FQ01la90zoKjitGxLr5ZAqkH0ZlrJYIm9vGZXSeuasPu47yxOxI":{"ts":1555942921965,"c1":{"halaman":"1","type":1,"plano":2},"sum":{"jum":202}}},"sum":{"tSah":4,"sah":198,"janggal":0,"cakupan":1,"pas1":99,"jum":202,"pending":0,"pas2":99}},"3":{"c1":null,"photos":{"http://lh3.googleusercontent.com/NkQpqUo-_iMLjpVP2Ih1LS3iHSBq1K85tG5EzsmtvQaSDEYUidoeoxSWQMvteUbyjxDM71FsPb0hM9ZvMg":{"sum":{"jum":255,"pending":0},"ts":1555942998045,"c1":{"type":1,"plano":2,"halaman":"1"}},"http://lh3.googleusercontent.com/hsBSjVVIwJuFr1Jl4U5JN61mMZIk2O0tTRbiLABiMj2sbh_LgfDt3IpNC6MzZ0a-3dQSBwtnBS-9Hv2HACs":{"sum":{"pas1":98,"tSah":4,"sah":251,"pas2":153},"ts":1555942980161,"c1":{"plano":2,"halaman":"2","type":1}}},"sum":{"tSah":4,"sah":251,"janggal":0,"cakupan":1,"pas1":98,"jum":255,"pending":0,"pas2":153},"ts":1555942998045},"4":{"ts":1555943075809,"c1":null,"photos":{"http://lh3.googleusercontent.com/p0es6hPtuI2Nz9YA08Mc5d1MNUfi-lWP-ZPgmszVGy1SlDCjmfQ73M21YXLPCS6Y_erRMWS6yId6x1Laf3_2":{"c1":{"type":1,"plano":2,"halaman":"2"},"sum":{"tSah":4,"sah":189,"pas2":90,"pas1":99},"ts":1555943063516},"http://lh3.googleusercontent.com/gRZDy0RZjGvzt06DeH-_aKF1bWJD6NQu9P6Z93vjcW9yCXbrJsb2nP3QFzSBttBl04-xUFYt6RRj76hgzl8":{"c1":{"plano":2,"halaman":"1","type":1},"sum":{"pending":0,"jum":193},"ts":1555943075809}},"sum":{"tSah":4,"sah":189,"janggal":0,"cakupan":1,"pas1":99,"jum":193,"pending":0,"pas2":90}},"5":{"c1":null,"photos":{"http://lh3.googleusercontent.com/nTIGPaffCUuzbxdfBUB2LE332-3JxJy_6OVhYe8PkH46eiruZjiIezWTU6cusLMFizU_FzP-90pQgn2MJQ4":{"ts":1555943140534,"c1":{"plano":2,"halaman":"1","type":1},"sum":{"jum":173,"pending":0}},"http://lh3.googleusercontent.com/mlK5bxwbP10vFsnKqf8UQ63I6NeS1ZyNAJqG15Pa0jUKUoEMePWhhq5DX7DKoi4k5EIU7e9wK6EAp1CU8q_u":{"c1":{"type":1,"plano":2,"halaman":"2"},"sum":{"pas1":58,"tSah":3,"sah":170,"pas2":112},"ts":1555943117688}},"sum":{"tSah":3,"sah":170,"janggal":0,"cakupan":1,"pas1":58,"jum":173,"pending":0,"pas2":112},"ts":1555943140534}},"parentIds":[0,20802,21702,21722],"name":"NAPAL","children":[[1,115,126],[2,116,118],[3,131,139],[4,105,124],[5,83,95]]}