{"parentNames":["IDN","JAWA TIMUR","BLITAR","DOKO"],"id":43583,"kpu":[null,{"pas1":174,"jum":192,"tSah":3,"sah":189,"pas2":15},{"tSah":1,"sah":143,"pas2":21,"pas1":122,"jum":144},{"tSah":0,"sah":128,"pas2":5,"pas1":123,"jum":128},{"pas2":13,"pas1":181,"jum":197,"tSah":3,"sah":194},{"tSah":3,"sah":155,"pas2":14,"pas1":141,"jum":158},{"tSah":3,"sah":106,"pas2":10,"pas1":96,"jum":109},{"pas2":18,"pas1":153,"jum":172,"tSah":1,"sah":171},{"tSah":3,"sah":138,"pas2":23,"pas1":115,"jum":141},{"pas2":21,"pas1":140,"jum":163,"tSah":2,"sah":161},{"tSah":5,"sah":223,"pas2":10,"pas1":213,"jum":228},{"tSah":9,"sah":227,"pas2":28,"pas1":199,"jum":236},{"pas2":37,"pas1":174,"jum":216,"tSah":5,"sah":211},{"tSah":2,"sah":154,"pas2":7,"pas1":147,"jum":156},{"pas2":18,"pas1":76,"jum":96,"tSah":94,"sah":2},{"tSah":2,"sah":97,"pas2":4,"pas1":93,"jum":99},{"tSah":5,"sah":94,"pas2":5,"pas1":89,"jum":99},{"tSah":1,"sah":133,"pas2":2,"pas1":131,"jum":134},{"tSah":0,"sah":83,"pas2":6,"pas1":77,"jum":83},{"tSah":2,"sah":63,"pas2":1,"pas1":62,"jum":65}],"depth":4,"data":{"0":{"c1":null,"photos":{},"sum":{"laporKpu":0,"pending":0,"janggal":0,"cakupan":0},"ts":0},"1":{"c1":null,"photos":{"http://lh3.googleusercontent.com/wBXtGRbFIUzBQLQdpZGpOJVnG_g7d1YqkVeN4pegfBQvP2YFnJ9bHKiJgqhneBLwVxE_uJ_S1jN6FnGt36g":{"ts":1556255362066,"c1":{"type":1,"plano":2,"halaman":"1"},"sum":{"jum":192}},"http://lh3.googleusercontent.com/rbW3dqocWlLPOGolzPo4lavoQShkZDqCCHjnIgSZSJoqIeYUdNMxNkpfXUQlu3R8FadpIpIGge_b54HRSg":{"c1":{"halaman":"2","type":1,"plano":2},"sum":{"tSah":3,"sah":189,"pending":0,"pas2":15,"pas1":174},"ts":1556255367930}},"sum":{"tSah":3,"sah":189,"janggal":0,"cakupan":1,"pas1":174,"jum":192,"pending":0,"pas2":15},"ts":1556255367930},"2":{"c1":null,"photos":{"http://lh3.googleusercontent.com/BleX4YgKnF97foeTqMNq5QMR743zLIFq_7peJ_9W59V3J4zzWWNRsxmGJSGJMoM5b1m8J_Vl9Onijf08OeKx":{"c1":{"plano":2,"halaman":"2","type":1},"sum":{"pas1":122,"tSah":1,"sah":143,"pas2":21},"ts":1556255375776},"http://lh3.googleusercontent.com/VT7XHXuAuFAsdNGZ40ltZc0-tdEDJ9iIdjYiVfj4VLoNdnDVsMHjN4R39LZnAl4oaqe0FIiumDYZQv812ZI":{"c1":{"halaman":"1","type":1,"plano":2},"sum":{"jum":144},"ts":1557727978672},"http://lh3.googleusercontent.com/H-0htW11EnXjcUQtOIkvGUi5FewXMItCoUdJRfDERYWpgP662TF6Fu-7if04nylkItnQAdPewby1otcZklc":{"c1":{"plano":1,"halaman":"2","type":1},"sum":{"pas1":122,"tSah":1,"sah":143,"pending":0,"pas2":21},"ts":1557728789929},"http://lh3.googleusercontent.com/7qN3yQloM6WtwRnNzbqCaoXbpHUGSyrGYTD1ilxrzcaHqlYHWAyawKSoJyEwJ1P_Rpz02DbNsQSiMOpQDGU":{"ts":1557727861156,"c1":{"type":1,"plano":1,"halaman":"2"},"sum":{"tSah":1,"sah":143,"pas2":21,"pas1":122}}},"sum":{"janggal":0,"cakupan":1,"pas1":122,"jum":144,"pending":0,"pas2":21,"tSah":1,"sah":143,"laporKpu":0},"ts":1557728789929},"3":{"c1":null,"photos":{"http://lh3.googleusercontent.com/LNTl29lEhy5Dpi0PROvg8uz38ZTNDlSDdBFvpjhPUy9WSR5AKpDgKfy5IJs3O8muxkqfNz45SHxF3Tk7C94":{"ts":1556255385488,"c1":{"type":1,"plano":2,"halaman":"2"},"sum":{"pas2":5,"pas1":123,"tSah":0,"sah":128}},"http://lh3.googleusercontent.com/i0mREoOc7th49BpD8c8MYy-pDQl7a7eU7qhMEh3p8X1K9_s07XRuM_jhbLPLvu3r2bFb77WJfqxexkLYog0":{"c1":{"type":1,"plano":2,"halaman":"1"},"sum":{"jum":128,"pending":0},"ts":1556255390140}},"sum":{"pending":0,"pas2":5,"tSah":0,"sah":128,"janggal":0,"cakupan":1,"pas1":123,"jum":128},"ts":1556255390140},"4":{"ts":1557728864712,"c1":null,"photos":{"http://lh3.googleusercontent.com/9FCgEmK6g2ukxoxmmRHBjFFcVQ9n3E1pAQ-1cy60kUtTOipK0LIbLO6dSyWsE0L9Se38sIpzPoTVbE4EQB8":{"sum":{"jum":197},"ts":1557728412887,"c1":{"type":1,"plano":1,"halaman":"1"}},"http://lh3.googleusercontent.com/Ma6Q8ycmc7EAc17EAPUbyq57dmuM0WXd8-OBGk7jgA3b-J1xbX8Zy_XE1wEtNMZvKSUJDzmNz2-ZG3gJU8Y":{"c1":{"type":1,"plano":2,"halaman":"2"},"sum":{"pas1":181,"tSah":3,"sah":194,"pas2":13},"ts":1556255398923},"http://lh3.googleusercontent.com/WhyAJy3Z6PlWq2-k5FTnZVMl2bj2GI7uVWOQOpSRsVqamkCYM38svOH0NWAf1KPts8ComwS7-9bU37vHJAo":{"c1":{"type":1,"plano":1,"halaman":"1"},"sum":{"pending":0,"jum":197},"ts":1557728864712},"http://lh3.googleusercontent.com/NvPm9TYRD2X4o2gwjDUKr1pqtZp9ZwSjSAxQ-ElNMRMfaTyUSGfIkRO7ATUVH0VufMcsRk7FYAGXvb-JeDg6":{"sum":{"jum":197},"ts":1556255408697,"c1":{"plano":2,"halaman":"1","type":1}}},"sum":{"janggal":0,"cakupan":1,"pas1":181,"jum":197,"pending":0,"pas2":13,"tSah":3,"sah":194,"laporKpu":0}},"5":{"c1":null,"photos":{"http://lh3.googleusercontent.com/VhBNEiKdbv95pHsQchJFrEaQb4llWqVlxid2R6_gv7_Kf243hmpbiraq2-uwjOo7XDcuC5dgbzcH_0W8fRk":{"c1":{"type":1,"plano":2,"halaman":"2"},"sum":{"pas1":141,"tSah":3,"sah":155,"pending":0,"pas2":14},"ts":1556255416591}},"sum":{"tSah":3,"sah":155,"janggal":0,"cakupan":1,"pas1":141,"pending":0,"pas2":14},"ts":1556255416591},"6":{"photos":{"http://lh3.googleusercontent.com/C0um_1Ek3nEhpSeZfiVHrz_qCk_i_nVyLAuP_9U329dNml2pVxR4uwwE-Yv59qEEnR-_1xJJeEieeT5JPg":{"sum":{"tSah":3,"sah":106,"pas2":10,"pas1":96},"ts":1557728763366,"c1":{"halaman":"2","type":1,"plano":1}},"http://lh3.googleusercontent.com/8z2rPv-GtB7txsfDTzI2B90T0q3wpt_X5xSiUZa0Gzky5GeQTYJWLVDXK1KbrcEGOEkaw5vxaSTfWXxx0Yun":{"sum":{"jum":109},"ts":1556255462963,"c1":{"halaman":"1","type":1,"plano":2}},"http://lh3.googleusercontent.com/vqfmH7X9hPzI_81IaJ4_XCM3qaRs8mj22YLWOTYg95iGTqyyS5pFUHs51URJ25Sta975ve1OuFoQ8ZZ2RHY":{"sum":{"pas1":96,"tSah":3,"sah":106,"pending":0,"pas2":10},"ts":1557729122604,"c1":{"type":1,"plano":1,"halaman":"2"}},"http://lh3.googleusercontent.com/XUHQMHu0K8f79XyOFWC6w5w4ybd4E6nGcruQ8kRs9XegzkWBTN7tK2oBgDOsB5sAY7ljomIQQhZpsfNq-5ad":{"sum":{"tSah":3,"sah":106,"pas2":10,"pas1":96},"ts":1556255448252,"c1":{"plano":2,"halaman":"2","type":1}}},"sum":{"tSah":3,"sah":106,"laporKpu":0,"janggal":0,"cakupan":1,"pas1":96,"jum":109,"pending":0,"pas2":10},"ts":1557729122604,"c1":null},"7":{"photos":{"http://lh3.googleusercontent.com/zbhCxq_518uAOtmq0LQuZn6bWBYHBV-XjX2aVeCXvWZUB8mmNmc_1XmvVU--FW122x8o9UnauX0TLupmMzw":{"sum":{"tSah":1,"sah":171,"pas2":18,"pas1":153},"ts":1556255501423,"c1":{"type":1,"plano":2,"halaman":"2"}},"http://lh3.googleusercontent.com/e2Hsvo5kJoWwhoXtfXaXQ0FOsqRtz4bpe3LWwCNheu8g80jQhWSsktsP9tmy2nK3bdxtfuFdUVn4ndm25iHo":{"sum":{"jum":172},"ts":1556255480526,"c1":{"type":1,"plano":2,"halaman":"1"}},"http://lh3.googleusercontent.com/9lXmLcgPDypcTU6nGY_z8DSRtF-G2YuTXR6g9PgCS0xXGCePA3pcnOMoOliibDNnnMQwmkjnKRBoAo73Bw":{"c1":{"halaman":"1","type":1,"plano":1},"sum":{"jum":172,"pending":0},"ts":1557728968370},"http://lh3.googleusercontent.com/mAtJ2acjujXtP1vQ6haKfC-StRVWJeCAy2dzvo7AD9VvsRhueGkshMD_bzuu86TQs3G7GiNEZa1i4OK_0Q":{"c1":{"type":1,"plano":1,"halaman":"2"},"sum":{"tSah":1,"sah":171,"pas2":18,"pas1":153},"ts":1557728590355}},"sum":{"janggal":0,"cakupan":1,"pas1":153,"jum":172,"pending":0,"pas2":18,"tSah":1,"sah":171,"laporKpu":0},"ts":1557728968370,"c1":null},"8":{"ts":1556928458330,"c1":null,"photos":{"http://lh3.googleusercontent.com/ZEgTfcbE6k55Awm-apRNsR8eiZajTgPPsV-1sBWLjb2yU_LJ1J_iXq7Kz94y_xrV6H4lsCsDi5Tz09lZ9LTg":{"c1":{"plano":2,"halaman":"1","type":1},"sum":{"jum":141},"ts":1556928453203},"http://lh3.googleusercontent.com/XOrWLsjJ04VGN5Fbt87osHl9unUjSwuYQf3USSNGcdqfnO3SsgSTLgO3LCTHLN0PUMCWhMiz4PaDcPcxedM":{"c1":{"halaman":"2","type":1,"plano":2},"sum":{"pas1":115,"tSah":3,"sah":138,"pending":0,"pas2":23},"ts":1556928458330}},"sum":{"pending":0,"pas2":23,"tSah":3,"sah":138,"janggal":0,"cakupan":1,"pas1":115,"jum":141}},"9":{"c1":null,"photos":{"http://lh3.googleusercontent.com/0hOWhXEzP2tG82KH9-EhV21gcV_hlz5h-MbNBbgfX-h1lkM43_--qjbcSijhuCtlMChkTxHkP9DuzcDoSQ":{"c1":{"type":1,"plano":2,"halaman":"1"},"sum":{"jum":163},"ts":1556255510693},"http://lh3.googleusercontent.com/xLxVgM8FRlwV0GU2-L6AMBPQ5TdY7LVk8R_V0yhhfxocBIOUjIrAdd5hKO7D3YEoxZI2uXQIKiP7hgnW7g":{"ts":1557728679797,"c1":{"plano":1,"halaman":"1","type":1},"sum":{"jum":163}},"http://lh3.googleusercontent.com/1ZK-XdG8a-gLD-V02avdHOPA6Dx0gJkuN33c72m1_eApNmi6Ck4yLZ6N6ktFgduTQovDojN3OlPu52K9gns":{"c1":{"halaman":"2","type":1,"plano":1},"sum":{"pas2":21,"pas1":140,"tSah":2,"sah":161,"pending":0},"ts":1557729078197},"http://lh3.googleusercontent.com/KB3Yzt1Jfl_ogAzQnYq2jMdCtc1r0CcUwTkOUEyJcPazyG49uNxlrYHszOTkc_0RNc5N8nfsDwVVcp6AhQDh":{"ts":1556255523797,"c1":{"halaman":"2","type":1,"plano":2},"sum":{"pas2":21,"pas1":140,"tSah":2,"sah":161}}},"sum":{"tSah":2,"sah":161,"laporKpu":0,"janggal":0,"cakupan":1,"pas1":140,"jum":163,"pending":0,"pas2":21},"ts":1557729078197},"10":{"c1":null,"photos":{"http://lh3.googleusercontent.com/HZyEWM4TQZE1RgboJhSaPA7Q-yhngF4sjH6f3luIvw4ZSpl7O6G2ZlzL7uWaJunnDL0n3MIp2WtLFeDUpBs":{"c1":{"plano":2,"halaman":"1","type":1},"sum":{"pending":0,"jum":228},"ts":1556255538889},"http://lh3.googleusercontent.com/QcdAbE_BKtMyWZj59yLawb307Tv0mNcIUJRLGVzLBGxghbrP8Tcv9DokyxBn9MvwJlrBemEgTAmhQ3WrIYk":{"sum":{"tSah":5,"sah":223,"pas2":10,"pas1":213},"ts":1556255533459,"c1":{"halaman":"2","type":1,"plano":2}}},"sum":{"pending":0,"pas2":10,"tSah":5,"sah":223,"janggal":0,"cakupan":1,"pas1":213,"jum":228},"ts":1556255538889},"11":{"c1":null,"photos":{"http://lh3.googleusercontent.com/Ggcq377-BLIv_kx2hsAEjoamJgKQ38cJ41Kx4QXfXaYPZBpnxccoS0xI5_xxp6hhPBOXLRAGKVIkLRAfMw":{"c1":{"type":1,"plano":2,"halaman":"2"},"sum":{"pas1":199,"tSah":9,"sah":227,"pending":0,"pas2":28},"ts":1556928475415},"http://lh3.googleusercontent.com/Ap0oFos6MSK-BgrUkoap_ymJ-RPTeqt7zXdO1HN08UjJgmvtwmv1Bt0-UatCjvUzZ22MoJH16B98m2q3c0o":{"ts":1556928470567,"c1":{"type":1,"plano":2,"halaman":"1"},"sum":{"jum":236}}},"sum":{"pending":0,"pas2":28,"tSah":9,"sah":227,"janggal":0,"cakupan":1,"pas1":199,"jum":236},"ts":1556928475415},"12":{"ts":1556255555672,"c1":null,"photos":{"http://lh3.googleusercontent.com/S87WDoDR3G7Y73u85WDeDQY9fxKo2frevjc9ilXDRurxFob2e5rtS8l4Fuj67m3-094psIDurw1EQ3rSCg":{"c1":{"type":1,"plano":2,"halaman":"2"},"sum":{"tSah":5,"sah":211,"pas2":37,"pas1":174},"ts":1556255548528},"http://lh3.googleusercontent.com/1cZEsX3iTaVBfJEQweTSbu0WWvBaAqPVjQaIfnWzAifdRIv_tTS2cTw9_-rQA08a6TTSuofg7wfojkQQbPq4":{"sum":{"pending":0,"jum":216},"ts":1556255555672,"c1":{"halaman":"1","type":1,"plano":2}}},"sum":{"janggal":0,"cakupan":1,"pas1":174,"jum":216,"pending":0,"pas2":37,"tSah":5,"sah":211}},"13":{"photos":{"http://lh3.googleusercontent.com/Q07QGazoMY9Qtp7e24w4jyb0ZYnj7zqq8bEXz8p55RepTD1NMH95eVyDCjyX2yPsmbhYInRExrjDAvp9eeE":{"sum":{"tSah":2,"sah":154,"pas2":7,"pas1":147},"ts":1556255564866,"c1":{"type":1,"plano":2,"halaman":"2"}},"http://lh3.googleusercontent.com/gWBo4yIuY_hiYxB4nJ6TBNJUIS3N3aAT_fPwPj-fLXF7Oa93RrycKkBrKlUtCl5KuBteQ6OSP3FhMVwnVxo":{"sum":{"pending":0,"jum":156},"ts":1556255570353,"c1":{"plano":2,"halaman":"1","type":1}}},"sum":{"tSah":2,"sah":154,"janggal":0,"cakupan":1,"pas1":147,"jum":156,"pending":0,"pas2":7},"ts":1556255570353,"c1":null},"14":{"c1":null,"photos":{"http://lh3.googleusercontent.com/JUsK0HsdnWhuggiqW-XQJjK95uZu6uph52ndTwXvcL-opilqr3diYns0sVryksgyRg5WFlF41O7WjLnX4SE":{"c1":{"type":1,"plano":2,"halaman":"1"},"sum":{"jum":96},"ts":1556255585171},"http://lh3.googleusercontent.com/NcrKNOsAiyqKZjE_8oD6tO4yLx44i3HKZJY9M6GqCA9B5Mo0b9OEtKcNu1kJmcAOUKxytvEecD0Z7hxhSnY":{"sum":{"tSah":2,"sah":94,"pending":0,"pas2":18,"pas1":76},"ts":1558246142385,"c1":{"plano":2,"halaman":"2","type":1}}},"sum":{"janggal":0,"cakupan":1,"pas1":76,"jum":96,"pending":0,"pas2":18,"tSah":2,"sah":94,"laporKpu":0},"ts":1558246142385},"15":{"c1":null,"photos":{"http://lh3.googleusercontent.com/m-AIQOg4yIoKx_QFExfWew6zLKoZZd2wrBBzxmUkz-k9hVPqffUBdczrKL_gBIYFrtr8UpvD6fT-NJwnpw":{"sum":{"tSah":2,"sah":97,"pas2":4,"pas1":93},"ts":1557728354743,"c1":{"plano":1,"halaman":"2","type":1}},"http://lh3.googleusercontent.com/mwVEJNmLLfj3H42KP_XKCd9QRIMGwwa6VJCag71tR0ajl6-QG2tu6NJV5LKbFRCY57tO4OzYZsiyC1sPsNs":{"ts":1556255595352,"c1":{"halaman":"2","type":1,"plano":2},"sum":{"tSah":2,"sah":97,"pas2":4,"pas1":93}},"http://lh3.googleusercontent.com/cGId3wpNr5KH3fSw0r5jUNPsR5zCG2QAHPmY12clcyWWgNzmL6bjqBZX8LmQMtcQPLfX2NNCPOyaOABKt7Y":{"c1":{"plano":2,"halaman":"1","type":1},"sum":{"jum":99},"ts":1556255600678},"http://lh3.googleusercontent.com/qUiguOZbLQqvbUp3q-mgsWLLukhlGPUmaloV3aqY64BkB5Qv5KT4S8OHYYKEq2WV3Y8Ymn16chhaWBRcrw":{"sum":{"jum":99,"pending":0},"ts":1557728819290,"c1":{"plano":1,"halaman":"1","type":1}}},"sum":{"tSah":2,"sah":97,"laporKpu":0,"janggal":0,"cakupan":1,"pas1":93,"jum":99,"pending":0,"pas2":4},"ts":1557728819290},"16":{"ts":1557728909905,"c1":null,"photos":{"http://lh3.googleusercontent.com/joHtc7HUk3wQTmznF34pPKUb95KcXbWkQTs7gOpLdVmOtYVXeoDi9fJPQXKj2vohQm1WgK29PnsVEZVMxovr":{"sum":{"jum":99},"ts":1556255616526,"c1":{"plano":2,"halaman":"1","type":1}},"http://lh3.googleusercontent.com/G_4szzJC8AIZzACUY_1eTo72zrZYl8utTZ5O2AMFt_x7ari7dUxq57ccKwLbvuccmeWYDpGJGbyxLWqqo5g":{"c1":{"type":1,"plano":1,"halaman":"2"},"sum":{"tSah":5,"sah":94,"pas2":5,"pas1":89},"ts":1557728501595},"http://lh3.googleusercontent.com/GsT4W2ilnPfGH0EyRqM6E8EwhAhQ0LU0pGU-u4gHsBbYVlp3FbhcC10ETCpMQu3iqi_VPNOgID9erQo4iRk2":{"c1":{"plano":2,"halaman":"2","type":1},"sum":{"tSah":5,"sah":94,"pas2":5,"pas1":89},"ts":1556255611049},"http://lh3.googleusercontent.com/YjU_12W8XqPLcIqu6zumfLAHb8oWe4nA30CrhVQvjVUjPgxGwClM2zmYJAXfNHKuPXbQQbUJlRdex2UtV-kQ":{"c1":{"plano":1,"halaman":"1","type":1},"sum":{"pending":0,"jum":99},"ts":1557728909905}},"sum":{"pas2":5,"tSah":5,"sah":94,"laporKpu":0,"janggal":0,"cakupan":1,"pas1":89,"jum":99,"pending":0}},"17":{"c1":null,"photos":{"http://lh3.googleusercontent.com/_HSM9YLWptJ7rzVKqJEQoPD4xym68aN_jsy-rhuZ-3dNtU0UwB249Dv7oH3YHz0nxN-lunmc2Aeujw3z5Q0":{"c1":{"plano":2,"halaman":"2","type":1},"sum":{"tSah":1,"sah":133,"pas2":2,"pas1":131},"ts":1556255630786},"http://lh3.googleusercontent.com/Ov8znvq5TkYy8Tnzzurqraoi9YmVjJDgnll33TT43aSnSZSONWf4lFPlbgt4xIH48I74rOyJjiaar_UgqA":{"c1":{"type":1,"plano":2,"halaman":"1"},"sum":{"jum":134,"pending":0},"ts":1556255635792}},"sum":{"pas2":2,"tSah":1,"sah":133,"janggal":0,"cakupan":1,"pas1":131,"jum":134,"pending":0},"ts":1556255635792},"18":{"ts":1557729003318,"c1":null,"photos":{"http://lh3.googleusercontent.com/QtF_gP2IC2-zdGT03ERp7w4f-2uQQxgfpJcfuc1UWLoPhmoFSj8esq5FP10KxkbG96w2w10lY4Ftr7N_uv4":{"c1":{"plano":2,"halaman":"2","type":1},"sum":{"tSah":0,"sah":83,"pas2":6,"pas1":77},"ts":1556255649730},"http://lh3.googleusercontent.com/BYblWtPjZXUUnw3K-xNc0leHuK6wEdMSYGkcmi5poRSXFAIiHcHcQ35Ll1b9Csp2dpW8fOPhWQE6FLwlGQ":{"c1":{"halaman":"2","type":1,"plano":1},"sum":{"tSah":0,"sah":83,"pending":0,"pas2":6,"pas1":77},"ts":1557729003318},"http://lh3.googleusercontent.com/w7SqgVBB_mshJnZnCKLlMwLBdhncoap_eFqGpvZQZ4WPNVxthizXkRDzQEbg9BcrdBs7rP_RLLaRExCvCg":{"c1":{"type":1,"plano":1,"halaman":"2"},"sum":{"pas2":6,"pas1":77,"tSah":0,"sah":83},"ts":1557728546644},"http://lh3.googleusercontent.com/5Nw7oPxRyZ3gMtkIs3qpNxghpP_To8n4VXTU50Eo_uGUui1EDcuCyoxs_-ZE8xG3DWZ0ippiD0MOmEBnhA":{"sum":{"jum":83},"ts":1556255655071,"c1":{"type":1,"plano":2,"halaman":"1"}},"http://lh3.googleusercontent.com/rsYzYzREoNEkYZ0xfHkDkVCdkmeW2YhA12DbTvlfZS3WEJ3tc01NCmM3iiTaKioRCAyEDw6ZKuFj_TZx_502":{"c1":{"type":1,"plano":1,"halaman":"2"},"sum":{"tSah":0,"sah":83,"pas2":6,"pas1":77},"ts":1557728626982},"http://lh3.googleusercontent.com/U1BrM7vVSlgP1-Zi5fwCLt8ek9W79nToOQMYK05jGB5QSIBbvoTX3guuUW5lbNySfQehntYjaocH-bca-H2f":{"sum":{"pas2":6,"pas1":77,"tSah":0,"sah":83},"ts":1557728950941,"c1":{"type":1,"plano":1,"halaman":"2"}}},"sum":{"janggal":0,"cakupan":1,"pas1":77,"jum":83,"pending":0,"pas2":6,"tSah":0,"sah":83,"laporKpu":0}},"19":{"c1":null,"photos":{"http://lh3.googleusercontent.com/R9DS2WEKjjBmNxDIMmGP2rYh1PK3HOONrSd1NUDmIdYJkAmkAHWu9b7NQ8QbNHzSdleYbdPFjli_nOWplAmf":{"c1":{"plano":2,"halaman":"1","type":1},"sum":{"jum":65,"pending":0},"ts":1557729192686},"http://lh3.googleusercontent.com/VhuSGHaOU1vUGwLBC0StZaLV3tIhyj3l78kQyMyMPugDHvgcsR4zltfu3aDQCLtMRUGpOQhR0Q9s62TwpkTA":{"ts":1556255663883,"c1":{"plano":2,"halaman":"2","type":1},"sum":{"tSah":2,"sah":63,"pas2":1,"pas1":62}},"http://lh3.googleusercontent.com/Fo_OGPwaPJBz9qLlYP6ioQZqHqwQHWoBR9yv8Gc4MugaShdUpZeRws5YNV_Ms7ZLgTjhCD1X8suTaYAGyfQ":{"ts":1557728438575,"c1":{"type":1,"plano":1,"halaman":"2"},"sum":{"pas1":62,"tSah":2,"sah":63,"pas2":1}},"http://lh3.googleusercontent.com/Himwu2Ws24FGPIVwL6YufXA_6xlS0wsS0H1Ui8Syvrp45Si9rtMvIOkEJJTZlfBqdOzDqayLsT8ppyk05YM":{"sum":{"jum":65},"ts":1557728890103,"c1":{"halaman":"1","type":1,"plano":1}}},"sum":{"tSah":2,"sah":63,"laporKpu":0,"janggal":0,"cakupan":1,"pas1":62,"jum":65,"pending":0,"pas2":1},"ts":1557729192686}},"parentIds":[0,42385,43360,43579],"name":"SUMBERURIP","children":[[1,131,122],[2,97,84],[3,97,71],[4,147,131],[5,108,91],[6,76,83],[7,112,109],[8,98,87],[9,91,102],[10,149,136],[11,139,146],[12,140,142],[13,96,92],[14,67,64],[15,69,65],[16,62,64],[17,83,86],[18,53,54],[19,42,38]]}