{"parentIds":[0,42385,44923,930148],"name":"KARANGREJO","parentNames":["IDN","JAWA TIMUR","BANYUWANGI","BLIMBINGSARI"],"id":45045,"kpu":[null,{"tSah":2,"sah":174,"pas2":42,"pas1":132,"jum":176},{"tSah":7,"sah":161,"pas2":50,"pas1":111,"jum":167},{"tSah":7,"sah":188,"pas2":45,"pas1":143,"jum":195},{"tSah":4,"sah":187,"pas2":41,"pas1":146,"jum":191},{"pas1":173,"jum":218,"tSah":4,"sah":214,"pas2":41},{"pas1":133,"jum":205,"tSah":2,"sah":203,"pas2":70},{"pas2":40,"pas1":152,"jum":200,"tSah":8,"sah":192},{"pas1":139,"jum":212,"tSah":4,"sah":208,"pas2":69},{"tSah":6,"sah":166,"pas2":33,"pas1":133,"jum":172},{"pas1":131,"jum":166,"tSah":3,"sah":163,"pas2":32},{"tSah":1,"sah":184,"pas2":40,"pas1":144,"jum":185}],"depth":4,"data":{"1":{"photos":{"http://lh3.googleusercontent.com/cKaObNNPT3COt62p3BDYL_nCwOJhS39h8X614NSNOrOfUafircnkRwxtqorDxhfGnz1aHcvJJBHamru6-znr":{"c1":{"halaman":"1","type":1,"plano":2},"sum":{"jum":176,"pending":0},"ts":1558304441722},"http://lh3.googleusercontent.com/7uECTaJxtViiNB1GukceyyOTH6TXI5jvpOfbvBFe5JonBDIkjkH2AljHLodJMJeLfHg2l8YGZR7WPHn4fc9Z":{"c1":{"type":1,"plano":2,"halaman":"2"},"sum":{"tSah":2,"sah":174,"pas2":42,"pas1":132},"ts":1558304436289}},"sum":{"tSah":2,"sah":174,"laporKpu":0,"janggal":0,"cakupan":1,"pas1":132,"jum":176,"pending":0,"pas2":42},"ts":1558304441722,"c1":null},"2":{"photos":{"http://lh3.googleusercontent.com/vFLNl_ubHystljfUKPSEULpQpvtP8xdoTETHqjKCWZ3AjRjk8DBtVMGNWKe6s165q6Dj1Xnf64tzdVOaVw":{"sum":{"tSah":7,"sah":161,"pas2":50,"pas1":111},"ts":1558304454618,"c1":{"plano":2,"halaman":"2","type":1}},"http://lh3.googleusercontent.com/g3XT8w1DcHxkL5JZjgrH2WR8mPQpTFjUY-9kZfKn78hwuJRVlXqGi0Ha7bDh_HYA-PCB2hnamAI-kwLn1d6y":{"c1":{"type":1,"plano":2,"halaman":"1"},"sum":{"jum":167},"ts":1558304460831}},"sum":{"pas2":50,"tSah":7,"sah":161,"laporKpu":1,"janggal":1,"cakupan":1,"pas1":111,"jum":167,"pending":0},"ts":1558304460831,"c1":null},"3":{"c1":null,"photos":{"http://lh3.googleusercontent.com/Bw-v5uuZ6Q3XnxJShatS_MBCHfrj30eQwOR6Kh4pN5ikHV1Eo9Wcv1sgY70g8Da2MrJrjFDzYLWqN3bhHeY":{"c1":{"plano":2,"halaman":"2","type":1},"sum":{"pas1":143,"tSah":7,"sah":188,"pending":0,"pas2":45},"ts":1556945045585},"http://lh3.googleusercontent.com/w_ZtKfVl3CJzy7gpLrosLnGaw5D3bxkOxR5FbrE3mPdiydQ1GB2uXUm8um1arferVHaX4HMxNeIaDAYLEs8":{"sum":{"jum":195},"ts":1556945032907,"c1":{"plano":2,"halaman":"1","type":1}}},"sum":{"pending":0,"pas2":45,"tSah":7,"sah":188,"janggal":0,"cakupan":1,"pas1":143,"jum":195},"ts":1556945045585},"4":{"photos":{"http://lh3.googleusercontent.com/NI3GRp3TspdISHaan0XaKepq4Q1bbLZTb4-xPcOtOV5VlzDQccyRpae7Jv9NavlxbeZAQi6lmisMr9d6EkdO":{"c1":{"plano":2,"halaman":"2","type":1},"sum":{"tSah":4,"sah":187,"pending":0,"pas2":41,"pas1":146},"ts":1556945074742},"http://lh3.googleusercontent.com/wp6kqOUSS50UARm7fNRCX-ekvoarodVjfplw-Cfup_29y7V7xbS_9oPjQTmI3Uy58cPemmhrHnTqTcNwFxk":{"c1":{"type":1,"plano":2,"halaman":"1"},"sum":{"jum":191},"ts":1556945062887}},"sum":{"tSah":4,"sah":187,"janggal":0,"cakupan":1,"pas1":146,"jum":191,"pending":0,"pas2":41},"ts":1556945074742,"c1":null},"5":{"c1":null,"photos":{"http://lh3.googleusercontent.com/HsMW2gSOhCTNALZ_dG2gno0FsOPKVVo_oU_KgnzrYNV7BQRK9-9s3G7vV2phawyCx1-tUWLBPB22Ol6Uels":{"c1":{"halaman":"2","type":1,"plano":2},"sum":{"sah":214,"pas2":41,"pas1":173,"tSah":4},"ts":1556945097024},"http://lh3.googleusercontent.com/3HkC9UNjoTPEtlmABsl909gIvHI4y6lhmdA2wX9JCAKW4GBWWSSUNhcXMmw1ZL_6h3QNDFoWiTw5ABNIvQ":{"sum":{"jum":218,"pending":0},"ts":1556945103023,"c1":{"type":1,"plano":2,"halaman":"1"}}},"sum":{"tSah":4,"sah":214,"janggal":0,"cakupan":1,"pas1":173,"jum":218,"pending":0,"pas2":41},"ts":1556945103023},"6":{"photos":{"http://lh3.googleusercontent.com/kw-ZGYkBoo1x_3VpsYgcohwAYOjycTVWCe1xgoePUidtbMpb6hEamofmq9gXAIUFL_k5DhIyu5OkByyJpg":{"c1":{"halaman":"1","type":1,"plano":2},"sum":{"jum":205},"ts":1556945118136},"http://lh3.googleusercontent.com/2_3qSD2qVCS0F5nvqtGen1oXJECOS8fpMPap4Nj3GRTmcfqXw5xM8qMwtai5AF4g678X5Rg-0uWmbeXqk_E":{"ts":1556945130585,"c1":{"type":1,"plano":2,"halaman":"2"},"sum":{"sah":203,"pending":0,"pas2":70,"pas1":133,"tSah":2}}},"sum":{"janggal":0,"cakupan":1,"pas1":133,"jum":205,"pending":0,"pas2":70,"tSah":2,"sah":203},"ts":1556945130585,"c1":null},"7":{"c1":null,"photos":{"http://lh3.googleusercontent.com/MKkBRJK2wPiGN-w09n7Oeki9INve3cxH8Azqc2ALU_9Q3K-Xd1Ps-p-SdBzYUi3JN3Aqy2moYtB6rLw4jg":{"c1":{"type":1,"plano":2,"halaman":"1"},"sum":{"pending":0,"jum":200},"ts":1556945153316},"http://lh3.googleusercontent.com/EKJSRXEOKIteJFJ1085F64LNUHC-fP6wdn6YNggg7TsLn67Uy7QblgE9j9ghWffGGEgbZW6KsV0mSEeFFC56":{"ts":1556945147742,"c1":{"plano":2,"halaman":"2","type":1},"sum":{"pas1":152,"tSah":8,"sah":192,"pas2":40}}},"sum":{"janggal":0,"cakupan":1,"pas1":152,"jum":200,"pending":0,"pas2":40,"tSah":8,"sah":192},"ts":1556945153316},"8":{"c1":null,"photos":{"http://lh3.googleusercontent.com/SZKee3bEKQ_Cr90wAbk64mQaFFJtY7ZiWz3SAchnHbad6Kd9DrkHYzp5_6ad0t5CO8-qJr3myUJHLhDEPnpL":{"c1":{"type":1,"plano":2,"halaman":"2"},"sum":{"pas1":139,"tSah":4,"sah":208,"pas2":69},"ts":1556945169668},"http://lh3.googleusercontent.com/rHV3n8ErDInvOyLBuNzzHDkmOiMM9we6JhZESfU5LgSkxmnHm4n1ORxU4SIyJtr1vgtT8Jku68kXR0Kq5A":{"sum":{"pending":0,"jum":212},"ts":1556945173868,"c1":{"type":1,"plano":2,"halaman":"1"}}},"sum":{"sah":208,"janggal":0,"cakupan":1,"pas1":139,"jum":212,"pending":0,"pas2":69,"tSah":4},"ts":1556945173868},"9":{"c1":null,"photos":{"http://lh3.googleusercontent.com/Bb5DoZhHN91ii-09Prkhs_7PqL0b8sg36T7tnC9lmTSN4YbhzfYI-UUJTk8AJai8nf7e0D6qDjbSwAq04vY":{"sum":{"pas1":133,"tSah":6,"sah":166,"pending":0,"pas2":33},"ts":1556945198758,"c1":{"type":1,"plano":2,"halaman":"2"}},"http://lh3.googleusercontent.com/-V2Q2tAm_bc-cFvIBYoiwDyw2G6sY-xaJbDxTX-VUAkniEKZdTh04FekKWoxatY0cwai6KwtVv_tySFmuXY":{"sum":{"jum":172},"ts":1556945190477,"c1":{"halaman":"1","type":1,"plano":2}}},"sum":{"tSah":6,"sah":166,"janggal":0,"cakupan":1,"pas1":133,"jum":172,"pending":0,"pas2":33},"ts":1556945198758},"10":{"c1":null,"photos":{"http://lh3.googleusercontent.com/8_jKdSqnqD0UKbd547E8zLm1a601UWA6WPOcXg5zjuSlSC-W0RzBVsTT_0GLQwWTfuGSFFCgI6ZbU3Nd54M":{"c1":{"plano":2,"halaman":"1","type":1},"sum":{"jum":166,"pending":0},"ts":1556945217607},"http://lh3.googleusercontent.com/_4ROIVgduq_DLcWqid_bUpWuHgUSgGkmCNyQTjGywcyoer2KvWCvMNzVsy6mUSAvi7CJRXL0hGIjtSiLSg":{"c1":{"plano":2,"halaman":"2","type":1},"sum":{"tSah":3,"sah":163,"pas2":32,"pas1":131},"ts":1556945212594}},"sum":{"tSah":3,"sah":163,"janggal":0,"cakupan":1,"pas1":131,"jum":166,"pending":0,"pas2":32},"ts":1556945217607},"11":{"photos":{"http://lh3.googleusercontent.com/Gtw7IG2TQovRyAEZeDCgYEyWE3iwYs8baE0zY7a7GDcEm3ikRb_KO9RpXftqHU3SNBkfl24hPlenoQxv1Ns":{"c1":{"type":1,"plano":2,"halaman":"2"},"sum":{"tSah":1,"sah":184,"pending":0,"pas2":40,"pas1":144},"ts":1556945255391},"http://lh3.googleusercontent.com/l2l-Re2vz1SdRqWBnlCwLHpqXdWZA89rezM8VjbtdN1siyL6Zyx9MlHlOG4T0yG9s7RVqhoGUHOVii34YQ":{"c1":{"type":1,"plano":2,"halaman":"1"},"sum":{"jum":185},"ts":1556945238415}},"sum":{"tSah":1,"sah":184,"janggal":0,"cakupan":1,"pas1":144,"jum":185,"pending":0,"pas2":40},"ts":1556945255391,"c1":null}},"children":[[1,142,130],[2,132,118],[3,124,121],[4,130,137],[5,132,138],[6,124,137],[7,124,124],[8,116,141],[9,124,127],[10,120,133],[11,132,143]]}