{"parentNames":["IDN","SULAWESI SELATAN","LUWU TIMUR","NUHA"],"id":72204,"kpu":[null,{"pas2":56,"pas1":80,"jum":136,"tSah":0,"sah":136},{"pas1":125,"jum":272,"tSah":2,"sah":270,"pas2":145},{"pas1":96,"jum":190,"tSah":0,"sah":190,"pas2":94},{"pas2":119,"pas1":118,"jum":238,"tSah":1,"sah":237},{"tSah":2,"sah":201,"pas2":103,"pas1":98,"jum":203},{"pas1":128,"jum":227,"tSah":0,"sah":227,"pas2":99},{"pas1":94,"jum":221,"tSah":1,"sah":220,"pas2":126},{"tSah":0,"sah":214,"pas2":123,"pas1":91,"jum":214},{"tSah":2,"sah":137,"pas2":76,"pas1":61,"jum":139},{"pas2":117,"pas1":72,"jum":190,"tSah":1,"sah":189},{"pas2":160,"pas1":70,"jum":233,"tSah":3,"sah":230},{"pas1":72,"jum":219,"tSah":1,"sah":218,"pas2":146},{"pas1":120,"jum":199,"tSah":2,"sah":197,"pas2":77},{"tSah":3,"sah":219,"pas2":103,"pas1":116,"jum":222}],"depth":4,"data":{"1":{"photos":{"http://lh3.googleusercontent.com/3NjVpKjBcDgHGNuFLRB0g5pLTXSAIGSIlpZiCSewtPnpwOOUr_abEAY5mIm2dA6F1xQujh9UrKAEOhedPRM":{"c1":{"plano":2,"halaman":"2","type":1},"sum":{"pas1":80,"tSah":0,"sah":136,"pas2":56},"ts":1556356311751},"http://lh3.googleusercontent.com/gefdj8f9X3UfwaCn-skqw8_o5fpn-SQztb4tOHBeIREnFEB0gcXpGEHdsRlQJMGdO8cG0M-O1IlKBpQRhaw":{"c1":{"type":1,"plano":1,"halaman":"2"},"sum":{"tSah":0,"sah":136,"pas2":56,"pas1":80},"ts":1555506778720},"http://lh3.googleusercontent.com/ZiIsueEKtPdhyUfhu6srKBg425M8ski27QWY8ZDp_DlAElZXmFsjcJHb8CZVbG26BncANmQ1j7hE6XroUxg":{"c1":{"type":1,"plano":1,"halaman":"2"},"sum":{"pas2":56,"pas1":80,"tSah":0,"sah":136,"pending":0},"ts":1556804620960},"http://lh3.googleusercontent.com/oppfhwXU6rU5mEb8N67IME-NjasPUh7A8kqRFfcITLgHSaTPk59DCBtpV5Zrxlv6-4pwYElBM2nUUwfBAjwl":{"ts":1556356319846,"c1":{"halaman":"1","type":1,"plano":2},"sum":{"jum":136}}},"sum":{"tSah":0,"sah":136,"janggal":0,"cakupan":1,"pas1":80,"jum":136,"pending":0,"pas2":56},"ts":1556804620960,"c1":null},"2":{"ts":1556358004128,"c1":null,"photos":{"http://lh3.googleusercontent.com/4N73fNiewwTftcX89btYY_8KQcHwhkLNJx3WdqVkwQEUDjpvZ711ablgPlkSA89glqpA6nu4Mvp2JCKJA_E":{"c1":{"plano":2,"halaman":"2","type":1},"sum":{"tSah":2,"sah":270,"pending":0,"pas2":145,"pas1":125},"ts":1556358004128},"http://lh3.googleusercontent.com/v_1iXl-T0JYEXMgV3703a6F6SjJTceCdeqZiLnNgGyyzcx4GzFwxN8RfLj8CKzyfRE89IYz5kUeLwSW07BZH":{"ts":1556356331793,"c1":{"plano":2,"halaman":"1","type":1},"sum":{"jum":272}},"http://lh3.googleusercontent.com/N1p-L33k5LCnycDEvjEx-_3r9SFOEm9JTxUm98qBOowbXorZn2xnKb5AY2OhqNF2zw-0mumUyJF_5_Vd9-A":{"ts":1555665543821,"c1":{"type":1,"plano":1,"halaman":"2"},"sum":{"pas2":145,"pas1":125,"tSah":2,"sah":270}}},"sum":{"janggal":0,"cakupan":1,"pas1":125,"jum":272,"pending":0,"pas2":145,"tSah":2,"sah":270}},"3":{"c1":null,"photos":{"http://lh3.googleusercontent.com/r1Ee_FtuiXVxONC0p3y-oYLwEXmyrYQWJxQgWeWSvOsO1nQxwcWdTGRMx_lsoW7yWosl0Dimt2SoR3zjClZT":{"c1":{"plano":2,"halaman":"2","type":1},"sum":{"tSah":0,"sah":190,"pending":0,"pas2":94,"pas1":96},"ts":1556358022079},"http://lh3.googleusercontent.com/ZMgq4_TjvoFRjFtFwSBe8fpZvSH3BXQ_bv_lbRyQf4OTDoE2pRo5UNXIig4EuMLUC8Kijr8iUp-BrnZEK_o":{"ts":1556358015989,"c1":{"plano":2,"halaman":"1","type":1},"sum":{"jum":190}}},"sum":{"tSah":0,"sah":190,"janggal":0,"cakupan":1,"pas1":96,"jum":190,"pending":0,"pas2":94},"ts":1556358022079},"4":{"ts":1556622926543,"c1":null,"photos":{"http://lh3.googleusercontent.com/3zfD6DP5FjihJwHwyhEYrHucSo2qRz4kaFnCv8rEHWwCV_QuploveiXDATeJLElMIvaYw3L77WN-owEERgY":{"sum":{"tSah":1,"sah":237,"pas2":119,"pas1":118},"ts":1556622920688,"c1":{"type":1,"plano":2,"halaman":"2"}},"http://lh3.googleusercontent.com/V7sZx4A7ES5TELQGGGlpnpCsQphenbx2xVjCNX8VuO4cCI8cRTbOPj6jicZi2OFiI-B8pA01ghNxIpwyCU9V":{"c1":{"type":1,"plano":2,"halaman":"1"},"sum":{"jum":238,"pending":0},"ts":1556622926543}},"sum":{"pending":0,"pas2":119,"tSah":1,"sah":237,"janggal":0,"cakupan":1,"pas1":118,"jum":238}},"5":{"c1":null,"photos":{"http://lh3.googleusercontent.com/nmY8aH7sL2F7aDTpuwpIJCqwSSayetqsUb0AB_gspUNg7sLONF8ILnOKJGBMSlknWirIOjudVdjLnSY6YwIa":{"sum":{"pas1":98,"tSah":2,"sah":201,"pas2":103},"ts":1556358039338,"c1":{"type":1,"plano":2,"halaman":"2"}},"http://lh3.googleusercontent.com/5sPQOFbVlomgKIU5_A2Yjrgi7lBRnsOMJlgMYSEdhi2xwGv9bMIlg3xdotRGnHR8y2URL2QwQVZf5DssSp4":{"c1":{"plano":2,"halaman":"1","type":1},"sum":{"jum":203},"ts":1556358032298}},"sum":{"janggal":0,"cakupan":1,"pas1":98,"jum":203,"pending":0,"pas2":103,"tSah":2,"sah":201,"laporKpu":0},"ts":1556358039338},"6":{"ts":1556358300048,"c1":null,"photos":{"http://lh3.googleusercontent.com/2wtqqQ0DvPEy5GzWTi9JzOpp2CKe5HPRpbGTueuuBA1KfIo3-jknCV-XscmymVsR4ugy6i5YV_qJipjgvg":{"c1":{"type":1,"plano":2,"halaman":"2"},"sum":{"pas2":99,"pas1":128,"tSah":0,"sah":227},"ts":1556358295515},"http://lh3.googleusercontent.com/T0pPMlS1n28wNRudgxPxc6Rh2ofSuf2j7xvAAhTPIt0l0YVk-xbFsuj43wQZP9EXGIyRQwD5ueyB8bgmDUKa":{"ts":1556358300048,"c1":{"halaman":"1","type":1,"plano":2},"sum":{"jum":227,"pending":0}}},"sum":{"pending":0,"pas2":99,"tSah":0,"sah":227,"janggal":0,"cakupan":1,"pas1":128,"jum":227}},"7":{"c1":null,"photos":{"http://lh3.googleusercontent.com/NHEBg3-5gYH8e0uKpcDR6qCNwWUzlz0Z9w2Ta_y6mjLP15CRmJeCig_rT5BfY54I2V-dqxoznW5qTn-h3mak":{"sum":{"tSah":1,"sah":220,"pending":0,"pas2":126,"pas1":94},"ts":1556358317397,"c1":{"type":1,"plano":2,"halaman":"2"}},"http://lh3.googleusercontent.com/9K2CX--Eq16so0qmeYCL8ph-lq91Yg5D__p9S5Q2UCLjHryD-mtAD10KiIIK4P8-7O9XzJ8lkBZT0RXNNTE":{"sum":{"jum":221},"ts":1556358310750,"c1":{"type":1,"plano":2,"halaman":"1"}}},"sum":{"tSah":1,"sah":220,"janggal":0,"cakupan":1,"pas1":94,"jum":221,"pending":0,"pas2":126},"ts":1556358317397},"8":{"c1":null,"photos":{"http://lh3.googleusercontent.com/Z-jLpq46lrWOwykgN88bI1fuvTtQMBr5RF1dXyyi2Z6dSCDY7IRr0oSw4yR6NLe29OCPgXFipHzjGUkHMLuQ":{"c1":{"halaman":"2","type":1,"plano":2},"sum":{"tSah":0,"sah":214,"pas2":123,"pas1":91},"ts":1556358326705},"http://lh3.googleusercontent.com/KDxYYlYL4jcgxgCP7PZiHHHDtHvSud7ZUpzfaS8uuOMeIksrWLOq-WqXZYgveI43uzyYD4t2WnXeQ-J9R7E":{"ts":1556358526939,"c1":{"plano":2,"halaman":"1","type":1},"sum":{"jum":214,"pending":0}}},"sum":{"tSah":0,"sah":214,"janggal":0,"cakupan":1,"pas1":91,"jum":214,"pending":0,"pas2":123},"ts":1556358526939},"9":{"photos":{"http://lh3.googleusercontent.com/zWkC85Gzq-YXyLhFOzOPHeTYAiGkHz4PeJoy8brAmkrKygwoL0vH0OsoKI9W-1hv12t6SNzJTmCSY0X_iUhl":{"ts":1556358543023,"c1":{"halaman":"1","type":1,"plano":2},"sum":{"pending":0,"jum":139}},"http://lh3.googleusercontent.com/fc4Uax5gsANtTifpO36H6wETUhq5RDMxjVJyj0zQNwmIiPCPk9sqGmd4aIyNQt-N9h4zuoAOvLQF1zjtquA":{"sum":{"tSah":2,"sah":137,"pas2":76,"pas1":61},"ts":1556358537350,"c1":{"plano":2,"halaman":"2","type":1}}},"sum":{"pending":0,"pas2":76,"tSah":2,"sah":137,"janggal":0,"cakupan":1,"pas1":61,"jum":139},"ts":1556358543023,"c1":null},"10":{"ts":1556358567701,"c1":null,"photos":{"http://lh3.googleusercontent.com/9NUlpNmgWnpKZyHVFsvRYYPjbEVyPD-SY3aL4ZsVSjQ8-8LGLbPPwWMC1Z4qJ7DCAL_vlPh1TH71S-ZO12g":{"sum":{"jum":190,"pending":0},"ts":1556358567701,"c1":{"type":1,"plano":2,"halaman":"1"}},"http://lh3.googleusercontent.com/nKFoWUBmCsPIHjPo3r6R1aB2YQOYLNdF1HADjOl53ByDi7nmqMSXz2w_UzQurT1umOO6OUgcwKZJE_ZY_g":{"sum":{"pas1":72,"tSah":1,"sah":189,"pas2":117},"ts":1556358562178,"c1":{"halaman":"2","type":1,"plano":2}}},"sum":{"janggal":0,"cakupan":1,"pas1":72,"jum":190,"pending":0,"pas2":117,"tSah":1,"sah":189}},"11":{"c1":null,"photos":{"http://lh3.googleusercontent.com/h8XDjEPQwOobNuEDwQM9h2zMdkotUzSHlizFyjRp7p_W-m961O_kQD1LR1O0DBbyvJNO_p3RxlqvYcnkr6jQ":{"c1":{"type":1,"plano":2,"halaman":"2"},"sum":{"tSah":3,"sah":230,"pas2":160,"pas1":70},"ts":1556358577617},"http://lh3.googleusercontent.com/40owVWcjVIWfBqBSgYTTx2yC-kyKI2HsNEjOpNdpkWGSg7YDmTsyjLDPHTkGZQt6qE7PjnkE4dGnWmHeQ7k":{"c1":{"type":1,"plano":2,"halaman":"1"},"sum":{"jum":233,"pending":0},"ts":1556358581772}},"sum":{"janggal":0,"cakupan":1,"pas1":70,"jum":233,"pending":0,"pas2":160,"tSah":3,"sah":230},"ts":1556358581772},"12":{"photos":{"http://lh3.googleusercontent.com/ldBg1ZUHFlUzxU8ujsQv4ZJ22d3mSZn5N35PayXb8Fn5JPT8G3MJYC9w0u6GJQ8_gMVCIb8-V8LuWSdtOA":{"sum":{"tSah":1,"sah":218,"pas2":146,"pas1":72},"ts":1556358592253,"c1":{"plano":2,"halaman":"2","type":1}},"http://lh3.googleusercontent.com/T6Q_RBs-bWdnHeHtIgJnmy0mfMtRF-r-J_zECghwOIL_2WioHRvjnWSH18KjUOBrbhe8quW6SznhRYP9VQk":{"ts":1556358596531,"c1":{"halaman":"1","type":1,"plano":2},"sum":{"pending":0,"jum":219}}},"sum":{"pending":0,"pas2":146,"tSah":1,"sah":218,"janggal":0,"cakupan":1,"pas1":72,"jum":219},"ts":1556358596531,"c1":null},"13":{"c1":null,"photos":{"http://lh3.googleusercontent.com/T5xNng60YGuoXPG5Jevh0mkoJB3KkQTZKf0mGeTBUBDjsWW-2JpqRqV0KrFT42uSO5uPvK2TKqrRRV4q0A":{"c1":{"type":1,"plano":2,"halaman":"2"},"sum":{"pas1":120,"tSah":2,"sah":197,"pas2":77},"ts":1556358606624},"http://lh3.googleusercontent.com/WrPIpouEkxf3-cEvMGZUclI1eMXIQgeD1zXxR2e2QAEQZz_d68-SLflgnn4nG8uNmMGZiBHa2_m8fspKLjs":{"c1":{"plano":2,"halaman":"1","type":1},"sum":{"jum":199},"ts":1556358612924}},"sum":{"pending":0,"pas2":77,"tSah":2,"sah":197,"laporKpu":0,"janggal":0,"cakupan":1,"pas1":120,"jum":199},"ts":1556358612924},"14":{"c1":null,"photos":{"http://lh3.googleusercontent.com/lewNQUlZc_LwlfhzhrWpuxPxQuQGxH9tSAFxf2l0zfYsE--m3PMZ-y_dtzTljyd0eRyDYhf4kk6UCGh7eJyp":{"c1":{"halaman":"2","type":1,"plano":1},"sum":{"pas1":116,"tSah":3,"sah":219,"pas2":103},"ts":1555771145174},"http://lh3.googleusercontent.com/RJjGpOXhTYTFhOmiUkh4uL0QAqVRccKvhCH7MnMWKQS7HQGeVH3qBua6m_RyrouFLcqYUaqQnO7Ouh8cdLU":{"ts":1556358917850,"c1":{"halaman":"1","type":1,"plano":2},"sum":{"jum":222}},"http://lh3.googleusercontent.com/CX759RjI9zLbbTlwBkbAGJh0GYAX9dh_jp81BbLGTdYwqtT2KuXgG-2VwLMaskpCbk3nvlgeU1kfL-2PmKHZ":{"c1":{"halaman":"2","type":1,"plano":2},"sum":{"tSah":3,"sah":219,"pending":0,"pas2":103,"pas1":116},"ts":1556358922584}},"sum":{"janggal":0,"cakupan":1,"pas1":116,"jum":222,"pending":0,"pas2":103,"tSah":3,"sah":219},"ts":1556358922584}},"parentIds":[0,69268,72190,72200],"name":"MAGANI","children":[[1,88,101],[2,140,125],[3,161,121],[4,151,130],[5,152,132],[6,157,118],[7,148,131],[8,142,138],[9,93,76],[10,132,129],[11,155,132],[12,138,130],[13,141,122],[14,150,123]]}