{"parentIds":[0,75425,76047,76090],"name":"BARUGA DHUA","parentNames":["IDN","SULAWESI BARAT","MAJENE","BANGGAE TIMUR"],"id":76093,"kpu":[null,{"pas2":60,"pas1":69,"jum":134,"tSah":5,"sah":129},{"tSah":12,"sah":171,"pas2":70,"pas1":101,"jum":183},{"tSah":4,"sah":184,"pas2":78,"pas1":106,"jum":188},{"pas1":87,"jum":153,"tSah":6,"sah":147,"pas2":60},{"tSah":2,"sah":197,"pas2":125,"pas1":72,"jum":199},{"tSah":3,"sah":117,"pas2":47,"pas1":70,"jum":120}],"depth":4,"data":{"1":{"ts":1557206794975,"c1":null,"photos":{"http://lh3.googleusercontent.com/AbfSzNUXbVGUsy-nr53ziTI59dkOaudgFOdIOf3pAv2NOzxQSg-7vcel9NHRC8G-8GlWo8cExRIcF8KSg2A":{"ts":1557206791491,"c1":{"type":1,"plano":2,"halaman":"1"},"sum":{"jum":134}},"http://lh3.googleusercontent.com/SKbTccOvXqC5WCrauij4BPcDKDwc1DguEnz0OjMzIxF_4Yd81Je4775k5oYu2pBCHChX1_QNpWycQE7Hg6o":{"c1":{"plano":2,"halaman":"2","type":1},"sum":{"tSah":5,"sah":129,"pas2":60,"pas1":69},"ts":1556028254029},"http://lh3.googleusercontent.com/FukSCLqfF-8NMivvVt3TQ2WB1K4LW1K5oT0TuHHeGiKeJm4QOfEYsKAPDj6rB2WikTSbNxoDfHQxpUZ81As":{"ts":1557206794975,"c1":{"plano":2,"halaman":"2","type":1},"sum":{"tSah":5,"sah":129,"pending":0,"pas2":60,"pas1":69}}},"sum":{"janggal":0,"cakupan":1,"pas1":69,"jum":134,"pending":0,"pas2":60,"tSah":5,"sah":129,"laporKpu":0}},"2":{"c1":null,"photos":{"http://lh3.googleusercontent.com/ESwDm0V0f5vK-DWhZl-BvITIj2yxMUYkDHgp8NaBjj5ocqFivM0HWVD5FpknAa6aFrMZdJtRqjIhoa-1og":{"ts":1556028268688,"c1":{"halaman":"2","type":1,"plano":2},"sum":{"pas1":101,"tSah":12,"sah":171,"pas2":70}},"http://lh3.googleusercontent.com/h1t6DQQfygVJlyn1l3mz2j5bqFqpy5XuoUyNaln7sBs9tcXmjsLfnR9dYTc1b7p6NqXv6zINrMED3-oLOgQ":{"c1":{"halaman":"2","type":1,"plano":2},"sum":{"tSah":12,"sah":171,"pending":0,"pas2":70,"pas1":101},"ts":1557206806378},"http://lh3.googleusercontent.com/ou5MCGg-RkY8tkwFlu_32mJt97yt-gqBryMYx9dtSo8MMLM0NGFROB9kjGAT1UWm4my5FQO4vdEsSaag39Y":{"c1":{"type":1,"plano":2,"halaman":"1"},"sum":{"jum":183},"ts":1557206802679}},"sum":{"pas2":70,"tSah":12,"sah":171,"laporKpu":0,"janggal":0,"cakupan":1,"pas1":101,"jum":183,"pending":0},"ts":1557206806378},"3":{"c1":null,"photos":{"http://lh3.googleusercontent.com/Z6dNAum73s6tJWVlDFfmYfys5vIgsz7PlHn6EN59j7WNfduziRDRjjmvWsDFqJPeXo4LqxCPxcY13SaohoSi":{"sum":{"pas1":106,"tSah":4,"sah":184,"pas2":78},"ts":1556028288463,"c1":{"type":1,"plano":2,"halaman":"2"}},"http://lh3.googleusercontent.com/vjLoHu1TYwxqle_IX77J9WWMwcNH6Xliyf2fW0K39tAqcvU6ZpkPjoq8RfP3Bp0W7PiMSRarSyvHBUXpkbQ":{"c1":{"type":1,"plano":2,"halaman":"1"},"sum":{"pending":0,"jum":188},"ts":1557206817416},"http://lh3.googleusercontent.com/pwSAfFjnjhup0kKjTjE2ZSsQ-tvyqDdSfwD8RP-PJqwmZvceUIRWON9TU9ne-utxbMK3WKvYIG4uZp95DVwr":{"ts":1557206814637,"c1":{"type":1,"plano":2,"halaman":"2"},"sum":{"tSah":4,"sah":184,"pas2":78,"pas1":106}}},"sum":{"pending":0,"pas2":78,"tSah":4,"sah":184,"laporKpu":0,"janggal":0,"cakupan":1,"pas1":106,"jum":188},"ts":1557206817416},"4":{"ts":1557206830750,"c1":null,"photos":{"http://lh3.googleusercontent.com/oRdvti0V3C8m6Q7ZvtXhFpb0vUoh1vOl_FZ4p14vSAZIviuVMR9O5z2IV1D9EEMEAyI1DPRKcDgn_3MIrQ":{"c1":{"halaman":"2","type":1,"plano":2},"sum":{"pas2":60,"pas1":87,"tSah":6,"sah":147,"pending":0},"ts":1557206830750},"http://lh3.googleusercontent.com/Il5yno4AfU6B9V4Sh_wStc-VpQoydXSX-3Apkphx_-DBJp-a4H7zSjzD3Vr7ifAQG2sCfYbFCFsLDP44oQ":{"c1":{"plano":2,"halaman":"1","type":1},"sum":{"jum":153},"ts":1557206827281},"http://lh3.googleusercontent.com/tB7Mz4e3dGuQjqVtPhlfIRuIp6Ffww97wrWKb4olxHdMN2hzik0XEmWiGpV79In-lAwHUHK-zvHZhcCYVEI":{"c1":{"halaman":"2","type":1,"plano":2},"sum":{"pas1":87,"tSah":6,"sah":147,"pas2":60},"ts":1556028303326}},"sum":{"pending":0,"pas2":60,"tSah":6,"sah":147,"laporKpu":0,"janggal":0,"cakupan":1,"pas1":87,"jum":153}},"5":{"photos":{"http://lh3.googleusercontent.com/U3BgHpZYQVFufmR5G4UizAfzoKdfiEtMoG8SvhAIG-Pao9GfiThAgrCRXUxwdpd3DvgswtBgO9yYLwztSQ8l":{"c1":{"halaman":"1","type":1,"plano":2},"sum":{"jum":199,"pending":0},"ts":1557206848706},"http://lh3.googleusercontent.com/I2k7mH7zYpRelKy1LGzBuGln3ra_NO9hxq96A6Exi06swrVB6TFwPOAxxfbq9bq2pzM7mlqGeV7q090wD2Q":{"c1":{"type":1,"plano":2,"halaman":"2"},"sum":{"tSah":2,"sah":197,"pas2":125,"pas1":72},"ts":1557206844153}},"sum":{"pending":0,"pas2":125,"tSah":2,"sah":197,"laporKpu":0,"janggal":0,"cakupan":1,"pas1":72,"jum":199},"ts":1557206848706,"c1":null},"6":{"photos":{"http://lh3.googleusercontent.com/t64dvopOuHjrhU3tHVwHlSpm0GtheQX3--Q1HVyFYCM3YgSXQT54TtvFS-LjS88GG-T9iJW7rqO2ZWf4LjY":{"sum":{"tSah":3,"sah":117,"pas2":47,"pas1":70},"ts":1557206863925,"c1":{"type":1,"plano":2,"halaman":"2"}},"http://lh3.googleusercontent.com/hUaoDj0UzEoThmHR2_X1DOG296uh3U6akUYKvqheTFNR7C-1om69KAg5iKHWEoApfzpCpVfXs14bVYMcFiLi":{"c1":{"type":1,"plano":2,"halaman":"1"},"sum":{"pending":0,"jum":120},"ts":1557206867201},"http://lh3.googleusercontent.com/JBBTUqfn2-pjyfSlAh5JLRFJy9qxl8FsFXku077pruo5mJHdRmjs0kGsyqythK93PQ_bIIboF-q65-YAriI":{"ts":1556028318228,"c1":{"halaman":"2","type":1,"plano":2},"sum":{"tSah":3,"sah":117,"pas2":47,"pas1":70}}},"sum":{"janggal":0,"cakupan":1,"pas1":70,"jum":120,"pending":0,"pas2":47,"tSah":3,"sah":117,"laporKpu":0},"ts":1557206867201,"c1":null}},"children":[[1,82,68],[2,100,106],[3,96,107],[4,88,84],[5,113,114],[6,56,67]]}