{"parentIds":[0,14086,14630,14631],"name":"KELEBUK","parentNames":["IDN","RIAU","BENGKALIS","BENGKALIS"],"id":928938,"kpu":[null,{"tSah":8,"sah":178,"pas2":91,"pas1":87,"jum":186},{"pas1":37,"jum":223,"tSah":2,"sah":221,"pas2":184},{"pas2":150,"pas1":44,"jum":200,"tSah":6,"sah":194}],"depth":4,"data":{"1":{"ts":1556343585433,"c1":null,"photos":{"http://lh3.googleusercontent.com/FBjWXlf4LbBUMzwOjMzNDzvZza9GhFjmTnz8-UkSoh9GnFqwl5ZYTw0oM2Q8tXDq27mR66eKWa2KStPhOw":{"c1":{"type":1,"plano":2,"halaman":"1"},"sum":{"jum":186},"ts":1556343585433},"http://lh3.googleusercontent.com/gNzW0-ixNiMn0NG2UMFOiA4LX3t69k_lQbnQCGDNOJmdDiPoeYMuuD6yTJcVU_rmNEzAwT-RQwpZInslezY":{"c1":{"type":1,"plano":2,"halaman":"2"},"sum":{"tSah":8,"sah":178,"pas2":91,"pas1":87},"ts":1556343581335},"http://lh3.googleusercontent.com/4bqmBZ2Jb9Mn9q_Hx8qL8eMOpUoIA8egxUraqb5pi93DH3r1uBOiMG4NjsfeYt6L6xM-nLBC6QM2DY3jFoUp":{"ts":1555568996216,"c1":{"type":1,"plano":1,"halaman":"2"},"sum":{"tSah":8,"sah":177,"pas2":91,"pas1":86}}},"sum":{"pending":0,"pas2":91,"tSah":8,"sah":178,"laporKpu":1,"janggal":1,"cakupan":1,"pas1":87,"jum":186}},"2":{"ts":1561599808743,"c1":null,"photos":{"http://lh3.googleusercontent.com/V0BNlahJQnhUhWwf26Hlfr744npGnQL2If4haOKg8Wj_xP_48s8fmfIbMgtlQwMJyzq0HuEkCPdY8-4PhA":{"sum":{"jum":223},"ts":1561599803706,"c1":{"plano":2,"halaman":"1","type":1}},"http://lh3.googleusercontent.com/ctdp5hmC1yn4RpbdyFxYqyhx96qXZOpzhI14tbQXV8IKE9qHMDfwsB6d8IobxbDSGO-HtwiL4Rbm-iL2bw":{"sum":{"tSah":2,"sah":221,"pending":0,"pas2":184,"pas1":37},"ts":1561599808743,"c1":{"halaman":"2","type":1,"plano":2}}},"sum":{"tSah":2,"sah":221,"laporKpu":0,"janggal":0,"cakupan":1,"pas1":37,"jum":223,"pending":0,"pas2":184}},"3":{"photos":{"http://lh3.googleusercontent.com/tL4_nZ3kWFF5uTJxFZnA5IxIgqwLt5UubOUhbnJ7or40R6PM608TIqkGvM8sgmu_PAA_YdS4JRav76rqrU8":{"c1":{"type":1,"plano":2,"halaman":"1"},"sum":{"jum":200},"ts":1556343554105},"http://lh3.googleusercontent.com/NepSP7CX1WxxTtNbHEc_orni-Gtzg1ASJD5NusoMm0Jt_6xiE1SY_KCs6KAwuqlkhDM5R-W5GxVyaE_sp80":{"c1":{"type":1,"plano":2,"halaman":"2"},"sum":{"pas2":150,"pas1":44,"tSah":6,"sah":194,"pending":0},"ts":1556343566090}},"sum":{"janggal":0,"cakupan":1,"pas1":44,"jum":200,"pending":0,"pas2":150,"tSah":6,"sah":194},"ts":1556343566090,"c1":null}},"children":[[1,116,104],[2,124,116],[3,114,115]]}